{
  "version": 3,
  "cmakeMinimumRequired": {
    "major": 3,
    "minor": 22,
    "patch": 0
  },
  "configurePresets": [
    {
      "name": "windows-msvc",
      "displayName": "Windows MSVC (VS 18 2026, x64)",
      "generator": "Visual Studio 18 2026",
      "architecture": "x64",
      "binaryDir": "${sourceDir}/build"
    },
    {
      "name": "windows-ninja",
      "displayName": "Windows Ninja + MSVC",
      "generator": "Ninja Multi-Config",
      "binaryDir": "${sourceDir}/build-ninja",
      "cacheVariables": {
        "CMAKE_MSVC_RUNTIME_LIBRARY": "MultiThreaded$<$<CONFIG:Debug>:Debug>DLL"
      }
    }
  ],
  "buildPresets": [
    {
      "name": "windows-msvc-debug",
      "configurePreset": "windows-msvc",
      "configuration": "Debug"
    },
    {
      "name": "windows-ninja-debug",
      "configurePreset": "windows-ninja",
      "configuration": "Debug"
    }
  ]
}
